LICENSE
MANIFEST.in
README.md
setup.py
data/published.json
docs/CONTRIBUTING.md
docs/conf.py
docs/docs-requirements.txt
docs/index.rst
docs/nucleic.base.rst
docs/nucleic.constants.rst
docs/nucleic.figures.rst
docs/nucleic.rst
docs/nucleic.sequence.rst
docs/nucleic.util.rst
docs/tutorial.rst
nucleic/__init__.py
nucleic/constants.py
nucleic/figures.py
nucleic/sequence.py
nucleic/signatures.py
nucleic/util.py
nucleic.egg-info/PKG-INFO
nucleic.egg-info/SOURCES.txt
nucleic.egg-info/dependency_links.txt
nucleic.egg-info/not-zip-safe
nucleic.egg-info/requires.txt
nucleic.egg-info/top_level.txt