Metadata-Version: 2.1
Name: nucleic
Version: 0.6.3
Summary: A Python 3.6 library for plotting mutational spectra.
Home-page: https://github.com/clintval/nucleic
Author: clintval
Author-email: valentine.clint@gmail.com
License: MIT
Download-URL: https://github.com/clintval/nucleic/archive/v0.6.3.tar.gz
Project-URL: Documentation, https://nucleic.readthedocs.io
Project-URL: Issue-Tracker, https://github.com/clintval/nucleic/issues
Keywords: signature mutation transition transversion spectra bioinformatics
Platform: UNKNOWN
Classifier: Development Status :: 2 - Pre-Alpha
Classifier: Intended Audience :: Developers
Classifier: Intended Audience :: Science/Research
Classifier: License :: OSI Approved :: MIT License
Classifier: Topic :: Scientific/Engineering :: Bio-Informatics
Classifier: Programming Language :: Python :: 3.6
Classifier: Programming Language :: Python :: 3.7
